ast_match/__init__.py
ast_match/_pattern.py
ast_match/parse.py
ast_match/pattern.py
ast_match-0.1.0.dist-info/LICENSE
ast_match-0.1.0.dist-info/METADATA
ast_match-0.1.0.dist-info/WHEEL
ast_match-0.1.0.dist-info/top_level.txt
ast_match-0.1.0.dist-info/zip-safe
ast_match-0.1.0.dist-info/RECORD
