Metadata-Version: 2.1
Name: ast-match
Version: 0.1.0
Summary: A library to facilitate easier manipulation of Python AST (abstract syntax tree) objects.
Home-page: https://github.com/user202729/ast-match
Author: user202729
License: GNU General Public License v3 or later (GPLv3+)
Classifier: License :: OSI Approved :: GNU General Public License v3 or later (GPLv3+)
Classifier: Operating System :: OS Independent
Classifier: Programming Language :: Python :: 3
License-File: LICENSE
